topsis/__init__.py
topsis/topsis.py
topsispackage3280-0.3.dist-info/METADATA
topsispackage3280-0.3.dist-info/WHEEL
topsispackage3280-0.3.dist-info/top_level.txt
topsispackage3280-0.3.dist-info/RECORD
